{

    "user_name": "om purwar",
    "adhaar_no": "2313123412341234",
    "nationality": "indian",
    "name": {
        "first_name": "Utkarsh",
        "middle_name": "",
        "last_name": "Pandey"
    },
    "contact": {
        "email": "utkarshpandey@gmail.com",
        "mob_no": 8933876208,
        "address": {
            "street": "raman house",
            "landmark": "rama university",
            "city": "kanpur",
            "state": "uttar pradesh",
            "pin_code": "209217",
            "country": "india"
        }
    },
    "sex": "male",
    "age": 23,
    "famiely_no": 4,
    "kids": 0,
    "device_owned": [""],
    "credentials": {
        "salt": "",
        "pass": ""
    },
    "active_flag": true,



    "device_id": ObjectId(''),
    "state_array": [{
            "Id": 3,
            "state": true
        },
        {
            "Id": 4,
            "state": true
        }
    ],
    "Current": 1.1,
    "req_made_timeStamp": "1",
    "req_land_timeStamp": "2",
    "timeStamp": "6526592230956728321"

}